ccraft/__init__.py
ccraft/__main__.py
ccraft-1.0.0a0.dist-info/LICENSE
ccraft-1.0.0a0.dist-info/METADATA
ccraft-1.0.0a0.dist-info/WHEEL
ccraft-1.0.0a0.dist-info/entry_points.txt
ccraft-1.0.0a0.dist-info/top_level.txt
ccraft-1.0.0a0.dist-info/RECORD
