Metadata-Version: 2.1
Name: ccraft
Version: 1.0.0a0
Summary: Modern automated build system for C/C++ projects, similar to GNU Make, but simpler and more powerful
Author-email: Eugene Azimut <y.azimut@mail.ru>
Project-URL: Homepage, https://github.com/yazimut/ccraft
Project-URL: Repository, https://github.com/yazimut/ccraft
Project-URL: Issues, https://github.com/yazimut/ccraft/issues
Project-URL: Changelog, https://github.com/yazimut/ccraft/blob/master/changelog.txt
Keywords: ccraft,C,C++,C/C++,build,system
Classifier: Programming Language :: Python :: 3
Classifier: License :: OSI Approved :: MIT License
Classifier: Operating System :: OS Independent
Requires-Python: >=3.12.3
License-File: LICENSE
